MANIFEST.in
README.rst
setup.py
tutor_richie.egg-info/PKG-INFO
tutor_richie.egg-info/SOURCES.txt
tutor_richie.egg-info/dependency_links.txt
tutor_richie.egg-info/entry_points.txt
tutor_richie.egg-info/requires.txt
tutor_richie.egg-info/top_level.txt
tutorrichie/__about__.py
tutorrichie/__init__.py
tutorrichie/plugin.py
tutorrichie/patches/.gitignore
tutorrichie/patches/caddyfile
tutorrichie/patches/k8s-deployments
tutorrichie/patches/k8s-jobs
tutorrichie/patches/k8s-services
tutorrichie/patches/kustomization
tutorrichie/patches/kustomization-configmapgenerator
tutorrichie/patches/local-docker-compose-dev-services
tutorrichie/patches/local-docker-compose-jobs-services
tutorrichie/patches/local-docker-compose-services
tutorrichie/patches/openedx-cms-development-settings
tutorrichie/patches/openedx-cms-production-settings
tutorrichie/patches/openedx-common-settings
tutorrichie/patches/openedx-development-settings
tutorrichie/patches/openedx-dockerfile-post-python-requirements
tutorrichie/patches/openedx-lms-development-settings
tutorrichie/patches/openedx-lms-production-settings
tutorrichie/templates/richie/apps/.gitignore
tutorrichie/templates/richie/apps/env.d/development
tutorrichie/templates/richie/apps/env.d/production
tutorrichie/templates/richie/apps/settings/tutor.py
tutorrichie/templates/richie/build/.gitignore
tutorrichie/templates/richie/build/richie/Dockerfile
tutorrichie/templates/richie/hooks/.gitignore
tutorrichie/templates/richie/hooks/mysql/init
tutorrichie/templates/richie/hooks/richie/init
tutorrichie/templates/richie/hooks/richie-openedx/init