Metadata-Version: 1.2
Name: tutor-richie
Version: 14.0.0
Summary: richie plugin for Tutor
Home-page: https://github.com/overhangio/tutor-richie
Author: Overhang.IO
License: AGPLv3
Project-URL: Code, https://github.com/overhangio/tutor-richie
Project-URL: Issue tracker, https://github.com/overhangio/tutor-richie/issues
Platform: UNKNOWN
Classifier: Development Status :: 5 - Production/Stable
Classifier: Intended Audience :: Developers
Classifier: License :: OSI Approved :: GNU Affero General Public License v3
Classifier: Operating System :: OS Independent
Classifier: Programming Language :: Python
Classifier: Programming Language :: Python :: 3.7
Classifier: Programming Language :: Python :: 3.8
Classifier: Programming Language :: Python :: 3.9
Classifier: Programming Language :: Python :: 3.10
Requires-Python: >=3.5
